ceaser_encryption/__init__.py
ceaser_encryption/cipher_proj.py
Caesar_Cipher22-0.1.0.dist-info/METADATA
Caesar_Cipher22-0.1.0.dist-info/WHEEL
Caesar_Cipher22-0.1.0.dist-info/top_level.txt
Caesar_Cipher22-0.1.0.dist-info/RECORD
