Metadata-Version: 2.1
Name: Caesar_Cipher22
Version: 0.1.0
Summary: A package for Caesar Cipher encryption and decryption
Home-page: https://github.com/yourusername/CaesarCipher
Author: Your Name
Author-email: your.email@example.com
Classifier: Programming Language :: Python :: 3
Classifier: License :: OSI Approved :: MIT License
Classifier: Operating System :: OS Independent
Requires-Python: >=3.6
